cscapi/__init__.py
cscapi/_version.py
cscapi/client.py
cscapi/mongodb_storage.py
cscapi/sql_storage.py
cscapi/storage.py
cscapi/utils.py
cscapi-0.7.0.dist-info/LICENSE
cscapi-0.7.0.dist-info/METADATA
cscapi-0.7.0.dist-info/WHEEL
cscapi-0.7.0.dist-info/top_level.txt
cscapi-0.7.0.dist-info/RECORD
