Metadata-Version: 2.1
Name: cscapi
Version: 0.7.0
Summary: CrowdSec SDK for CAPI
Home-page: https://github.com/crowdsecurity/python-capi-sdk
Author: CrowdSec
Author-email: core.tech@crowdsec.net
Project-URL: Bug Tracker, https://github.com/crowdsecurity/python-capi-sdk/issues
Classifier: Programming Language :: Python :: 3
Classifier: Operating System :: OS Independent
Classifier: License :: OSI Approved :: MIT License
Requires-Python: >=3.9
License-File: LICENSE
Requires-Dist: sqlalchemy >=1.4
Requires-Dist: python-dateutil
Requires-Dist: httpx ==0.26.*
Requires-Dist: dacite
Requires-Dist: importlib-metadata
Requires-Dist: pyjwt
Requires-Dist: more-itertools
Provides-Extra: mongodb
Requires-Dist: mongoengine ; extra == 'mongodb'
